ukis_pysat/__init__.py
ukis_pysat/file.py
ukis_pysat/members.py
ukis_pysat/raster.py
ukis_pysat-1.5.1.dist-info/LICENSE.txt
ukis_pysat-1.5.1.dist-info/METADATA
ukis_pysat-1.5.1.dist-info/WHEEL
ukis_pysat-1.5.1.dist-info/top_level.txt
ukis_pysat-1.5.1.dist-info/RECORD
