Metadata-Version: 2.1
Name: ukis-pysat
Version: 1.5.1
Summary: generic classes and functions to query, access and process multi-spectral and SAR satellite images
Home-page: https://github.com/dlr-eoc/ukis-pysat
Author: German Aerospace Center (DLR)
Author-email: ukis-helpdesk@dlr.de
License: Apache 2.0
Classifier: Programming Language :: Python :: 3
Classifier: Operating System :: OS Independent
Classifier: Development Status :: 4 - Beta
Classifier: License :: OSI Approved :: Apache Software License
Classifier: Topic :: Scientific/Engineering :: GIS
Requires-Python: >=3.7
License-File: LICENSE.txt
Provides-Extra: complete
Requires-Dist: shapely ; extra == 'complete'
Requires-Dist: rasterio (>=1.1.8) ; extra == 'complete'
Requires-Dist: numpy ; extra == 'complete'
Requires-Dist: xmltodict ; extra == 'complete'
Requires-Dist: rio-toa (>=0.3.0) ; extra == 'complete'
Provides-Extra: dev
Requires-Dist: dask[array] ; extra == 'dev'
Requires-Dist: fiona ; extra == 'dev'
Requires-Dist: numpy ; extra == 'dev'
Requires-Dist: pandas ; extra == 'dev'
Requires-Dist: pyproj (>=3.0.0) ; extra == 'dev'
Requires-Dist: rasterio (>=1.1.8) ; extra == 'dev'
Requires-Dist: rio-toa (>=0.3.0) ; extra == 'dev'
Requires-Dist: shapely ; extra == 'dev'
Requires-Dist: sphinx (>=1.3) ; extra == 'dev'
Requires-Dist: sphinx-rtd-theme ; extra == 'dev'
Requires-Dist: utm (>=0.7.0) ; extra == 'dev'
Requires-Dist: xmltodict ; extra == 'dev'
Provides-Extra: raster
Requires-Dist: numpy ; extra == 'raster'
Requires-Dist: rasterio (>=1.1.8) ; extra == 'raster'
Requires-Dist: rio-toa (>=0.3.0) ; extra == 'raster'
Requires-Dist: shapely ; extra == 'raster'
Requires-Dist: xmltodict ; extra == 'raster'
